promptlabs/__init__.py
promptlabs/client.py
promptlabs/pipeline.py
promptlabs/chain/__init__.py
promptlabs/chain/base_chain.py
promptlabs/chain/function_chain.py
promptlabs/chain/llm_chain.py
promptlabs/scheme/llm.py
promptlabs/scheme/template.py
promptlabs-0.0.6.dist-info/LICENSE
promptlabs-0.0.6.dist-info/METADATA
promptlabs-0.0.6.dist-info/WHEEL
promptlabs-0.0.6.dist-info/top_level.txt
promptlabs-0.0.6.dist-info/RECORD
